{
  "meta": {
    "dump_utc": "26y01m16d1048c",
    "region": "ap-northeast-1",
    "service": "s3"
  },
  "data": {
    "list_buckets": {
      "ok": true,
      "label": "s3.list_buckets",
      "data": {
        "ResponseMetadata": {
          "RequestId": "0GJ20Z87QCW7F5HY",
          "HostId": "cvrEPIcw6anjYZIslLbw1I+Kfr1hWr+TqrMOISW3fN3srBkSjhYmp4tYZxIG+zlr1E/4IEN+yO4=",
          "HTTPStatusCode": 200,
          "HTTPHeaders": {
            "x-amz-id-2": "cvrEPIcw6anjYZIslLbw1I+Kfr1hWr+TqrMOISW3fN3srBkSjhYmp4tYZxIG+zlr1E/4IEN+yO4=",
            "x-amz-request-id": "0GJ20Z87QCW7F5HY",
            "date": "Fri, 16 Jan 2026 01:48:52 GMT",
            "content-type": "application/xml",
            "transfer-encoding": "chunked",
            "server": "AmazonS3"
          },
          "RetryAttempts": 0
        },
        "Buckets": [],
        "Owner": {
          "ID": "13db52b45fc036d280db52c58adfd09c164fc62b817aaa1fdc9f73945dd87df1"
        }
      }
    },
    "get_bucket_location": {
      "ok": true,
      "label": "s3.get_bucket_location",
      "data": []
    }
  }
}